sapiens/__init__.py
sapiens/__version__.py
sapiens/predict.py
sapiens-1.1.0.dist-info/LICENSE
sapiens-1.1.0.dist-info/LICENSES_THIRD_PARTY
sapiens-1.1.0.dist-info/METADATA
sapiens-1.1.0.dist-info/WHEEL
sapiens-1.1.0.dist-info/top_level.txt
sapiens-1.1.0.dist-info/RECORD
