Metadata-Version: 2.1
Name: sapiens
Version: 1.1.0
Summary: Sapiens: Human antibody language model based on BERT
Home-page: https://github.com/Merck/Sapiens
Author: David Prihoda
Author-email: david.prihoda@gmail.com
License: MIT
Keywords: sapiens,antibody humanization,bert,biophi
Classifier: Programming Language :: Python :: 3
Requires-Python: >=3.7
License-File: LICENSE
License-File: LICENSES_THIRD_PARTY
Requires-Dist: pandas
Requires-Dist: transformers
Requires-Dist: torch
